{
  "code": "marina",
  "sector": "maritime",
  "name": "Marina / Yacht Harbor",
  "description": "Marina with berth map, mooring contracts, utilities, boatyard, nautical shop",
  "icon": "boat-outline",
  "color": "#01579b",
  "inherits_from": [],
  "is_combinable": true,
  "ufo_matrix": {
    "FIN": "essential",
    "COM": "essential",
    "ALM": "essential",
    "TPV": "essential",
    "VEN": "essential",
    "CRM": "essential",
    "ECO": "essential",
    "PRO": "na",
    "LOG": "na",
    "RRH": "essential",
    "PRY": "essential",
    "BI": "essential"
  },
  "extra_modules": [],
  "sector_features": [
    "Berth map",
    "Mooring contracts",
    "Boatyard"
  ],
  "roles": [
    {
      "id": "manager",
      "name": "Manager",
      "permissions": [
        "*"
      ]
    }
  ],
  "products_file": "products/marina.json"
}