{
  "code": "consulting",
  "sector": "professional_services",
  "name": "Consulting / Advisory",
  "description": "Consulting or advisory firm with timesheet, hourly billing, project management, CRM pipeline, and contract management",
  "icon": "briefcase-outline",
  "color": "#1a237e",
  "is_combinable": true,
  "ufo_matrix": {
    "FIN": "na",
    "COM": "na",
    "ALM": "na",
    "TPV": "na",
    "VEN": "na",
    "CRM": "na",
    "ECO": "na",
    "PRO": "na",
    "LOG": "na",
    "RRH": "na",
    "PRY": "na",
    "BI": "na"
  },
  "extra_modules": [
    "contracts",
    "customers",
    "invoicing",
    "projects",
    "tasks",
    "tax",
    "time_control"
  ],
  "sector_features": [
    "Timesheet",
    "Hourly billing",
    "Project management",
    "CRM pipeline",
    "Contract management"
  ],
  "roles": [
    {
      "id": "consultant",
      "name": "Consultant",
      "permissions": [
        "projects.*",
        "tasks.*",
        "time_control.*",
        "customers.view_*"
      ]
    },
    {
      "id": "manager",
      "name": "Manager",
      "permissions": [
        "projects.*",
        "customers.*",
        "invoicing.*",
        "contracts.*",
        "reports.view_*"
      ]
    }
  ],
  "products_file": "products/consulting.json"
}
